datafixtures/__init__.py
datafixtures/entry.py
pytest_datafixtures-1.0.0.dist-info/AUTHORS
pytest_datafixtures-1.0.0.dist-info/LICENSE
pytest_datafixtures-1.0.0.dist-info/METADATA
pytest_datafixtures-1.0.0.dist-info/WHEEL
pytest_datafixtures-1.0.0.dist-info/entry_points.txt
pytest_datafixtures-1.0.0.dist-info/top_level.txt
pytest_datafixtures-1.0.0.dist-info/RECORD
